{
  "_class": "shapeGroup",
  "clippingMaskMode": 0,
  "do_objectID": "1C720B8A-E025-483E-93D1-7960C4CC46EF",
  "exportOptions": {
    "_class": "exportOptions",
    "exportFormats": [
    ],
    "includedLayerIds": [
    ],
    "layerOptions": 0,
    "shouldTrim": false
  },
  "frame": {
    "_class": "rect",
    "constrainProportions": false,
    "height": 351,
    "width": 1024,
    "x": 128,
    "y": 0
  },
  "hasClickThrough": false,
  "hasClippingMask": false,
  "isFlippedHorizontal": false,
  "isFlippedVertical": false,
  "isLocked": false,
  "isVisible": true,
  "layerListExpandedType": 0,
  "layers": [
    {
      "class": "rectangle",
      "id": "DE83623E-528B-490B-BD3A-4C594EE02F8C"
    }
  ],
  "name": "Sidebar Layout Container",
  "nameIsFixed": true,
  "resizingConstraint": 61,
  "resizingType": 0,
  "rotation": 0,
  "shouldBreakMaskChain": false,
  "style": {
    "sharedObjectID": "9B9D15FF-B456-479A-896A-B642865856EA"
  },
  "userInfo": {
    "com.animaapp.stc-sketch-plugin": {
      "kModelPropertiesKey": {
      }
    }
  },
  "windingRule": 1
}