{
  "_class": "shapePath",
  "booleanOperation": -1,
  "do_objectID": "4B571F8F-0D6E-43E5-94BD-8487A8C1553C",
  "edited": true,
  "exportOptions": {
    "_class": "exportOptions",
    "exportFormats": [
    ],
    "includedLayerIds": [
    ],
    "layerOptions": 0,
    "shouldTrim": false
  },
  "frame": {
    "_class": "rect",
    "constrainProportions": false,
    "height": 3.461658074780484,
    "width": 3.88714953252409,
    "x": 46.67287904509634,
    "y": 8.522402294341461
  },
  "isFlippedHorizontal": false,
  "isFlippedVertical": false,
  "isLocked": false,
  "isVisible": true,
  "layerListExpandedType": 0,
  "name": "path46-path",
  "nameIsFixed": false,
  "path": {
    "_class": "path",
    "isClosed": true,
    "pointRadiusBehaviour": 0,
    "points": [
      {
        "_class": "curvePoint",
        "cornerRadius": 0,
        "curveFrom": "{0.54838709677419351, 0}",
        "curveMode": 4,
        "curveTo": "{0.83587096774193659, 0}",
        "hasCurveFrom": false,
        "hasCurveTo": true,
        "point": "{0.54838709677419351, 0}"
      },
      {
        "_class": "curvePoint",
        "cornerRadius": 0,
        "curveFrom": "{0, 0}",
        "curveMode": 1,
        "curveTo": "{0, 0}",
        "hasCurveFrom": false,
        "hasCurveTo": false,
        "point": "{0, 0}"
      },
      {
        "_class": "curvePoint",
        "cornerRadius": 0,
        "curveFrom": "{0, 1}",
        "curveMode": 1,
        "curveTo": "{0, 1}",
        "hasCurveFrom": false,
        "hasCurveTo": false,
        "point": "{0, 1}"
      },
      {
        "_class": "curvePoint",
        "cornerRadius": 0,
        "curveFrom": "{0.83587096774193659, 1}",
        "curveMode": 4,
        "curveTo": "{0.54838709677419351, 1}",
        "hasCurveFrom": true,
        "hasCurveTo": false,
        "point": "{0.54838709677419351, 1}"
      },
      {
        "_class": "curvePoint",
        "cornerRadius": 0,
        "curveFrom": "{1, 0.27442403032954193}",
        "curveMode": 2,
        "curveTo": "{1, 0.73024205307669843}",
        "hasCurveFrom": true,
        "hasCurveTo": true,
        "point": "{1, 0.50014581510644518}"
      }
    ]
  },
  "resizingConstraint": 63,
  "resizingType": 0,
  "rotation": 0,
  "shouldBreakMaskChain": false
}