{
  "_class": "shapePath",
  "booleanOperation": -1,
  "do_objectID": "2209E50A-FE1D-4DD7-A455-AF0EA313FDC7",
  "edited": true,
  "exportOptions": {
    "_class": "exportOptions",
    "exportFormats": [
    ],
    "includedLayerIds": [
    ],
    "layerOptions": 0,
    "shouldTrim": false
  },
  "frame": {
    "_class": "rect",
    "constrainProportions": false,
    "height": 17,
    "width": 24,
    "x": 0,
    "y": 0
  },
  "isClosed": true,
  "isFlippedHorizontal": false,
  "isFlippedVertical": false,
  "isLocked": false,
  "isVisible": true,
  "layerListExpandedType": 0,
  "name": "Path",
  "nameIsFixed": false,
  "pointRadiusBehaviour": 1,
  "points": [
    {
      "_class": "curvePoint",
      "cornerRadius": 0,
      "curveFrom": "{0.33333333333333331, 0}",
      "curveMode": 4,
      "curveTo": "{0.32228264625668573, 0}",
      "hasCurveFrom": false,
      "hasCurveTo": true,
      "point": "{0.33333333333333331, 0}"
    },
    {
      "_class": "curvePoint",
      "cornerRadius": 0,
      "curveFrom": "{0.96269039581923277, 0}",
      "curveMode": 4,
      "curveTo": "{0.91666666666666663, 0}",
      "hasCurveFrom": true,
      "hasCurveTo": false,
      "point": "{0.91666666666666663, 0}"
    },
    {
      "_class": "curvePoint",
      "cornerRadius": 0,
      "curveFrom": "{1, 0.11764705882352941}",
      "curveMode": 4,
      "curveTo": "{1, 0.052672382372847854}",
      "hasCurveFrom": false,
      "hasCurveTo": true,
      "point": "{1, 0.11764705882352941}"
    },
    {
      "_class": "curvePoint",
      "cornerRadius": 0,
      "curveFrom": "{1, 0.94732761762715212}",
      "curveMode": 4,
      "curveTo": "{1, 0.88235294117647056}",
      "hasCurveFrom": true,
      "hasCurveTo": false,
      "point": "{1, 0.88235294117647056}"
    },
    {
      "_class": "curvePoint",
      "cornerRadius": 0,
      "curveFrom": "{0.91666666666666663, 1}",
      "curveMode": 4,
      "curveTo": "{0.96269039581923277, 1}",
      "hasCurveFrom": false,
      "hasCurveTo": true,
      "point": "{0.91666666666666663, 1}"
    },
    {
      "_class": "curvePoint",
      "cornerRadius": 0,
      "curveFrom": "{0.037309604180767231, 1}",
      "curveMode": 4,
      "curveTo": "{0.083333333333333329, 1}",
      "hasCurveFrom": true,
      "hasCurveTo": false,
      "point": "{0.083333333333333329, 1}"
    },
    {
      "_class": "curvePoint",
      "cornerRadius": 0,
      "curveFrom": "{0, 0.88235294117647056}",
      "curveMode": 4,
      "curveTo": "{0, 0.94732761762715212}",
      "hasCurveFrom": false,
      "hasCurveTo": true,
      "point": "{0, 0.88235294117647056}"
    },
    {
      "_class": "curvePoint",
      "cornerRadius": 0,
      "curveFrom": "{0, 0.20280677942171804}",
      "curveMode": 4,
      "curveTo": "{0, 0.23529411764705882}",
      "hasCurveFrom": true,
      "hasCurveTo": false,
      "point": "{0, 0.23529411764705882}"
    },
    {
      "_class": "curvePoint",
      "cornerRadius": 0,
      "curveFrom": "{0.041666666666666664, 0.17647058823529413}",
      "curveMode": 4,
      "curveTo": "{0.018654802090383615, 0.17647058823529413}",
      "hasCurveFrom": false,
      "hasCurveTo": true,
      "point": "{0.041666666666666664, 0.17647058823529413}"
    },
    {
      "_class": "curvePoint",
      "cornerRadius": 0,
      "curveFrom": "{0.27301186457628307, 0.17647058823529413}",
      "curveMode": 4,
      "curveTo": "{0.25, 0.17647058823529413}",
      "hasCurveFrom": true,
      "hasCurveTo": false,
      "point": "{0.25, 0.17647058823529413}"
    },
    {
      "_class": "curvePoint",
      "cornerRadius": 0,
      "curveFrom": "{0.29166666666666669, 0.11764705882352941}",
      "curveMode": 4,
      "curveTo": "{0.29166666666666669, 0.15013439704887019}",
      "hasCurveFrom": false,
      "hasCurveTo": true,
      "point": "{0.29166666666666669, 0.11764705882352941}"
    },
    {
      "_class": "curvePoint",
      "cornerRadius": 0,
      "curveFrom": "{0.29166666666666669, 0.043222559421203309}",
      "curveMode": 4,
      "curveTo": "{0.29166666666666669, 0.058823529411764705}",
      "hasCurveFrom": true,
      "hasCurveTo": false,
      "point": "{0.29166666666666669, 0.058823529411764705}"
    },
    {
      "_class": "curvePoint",
      "cornerRadius": 0,
      "curveFrom": "{0.31168456655256205, 0.0061974611979657476}",
      "curveMode": 2,
      "curveTo": "{0.29605653501522577, 0.028260564544793323}",
      "hasCurveFrom": true,
      "hasCurveTo": true,
      "point": "{0.30387055078389391, 0.017229012871379536}"
    }
  ],
  "resizingConstraint": 63,
  "resizingType": 0,
  "rotation": 0,
  "shouldBreakMaskChain": false
}