{
  "_class": "group",
  "do_objectID": "CBBCBFCD-0880-483F-BCC6-9C0D2585C66F",
  "exportOptions": {
    "_class": "exportOptions",
    "exportFormats": [
    ],
    "includedLayerIds": [
    ],
    "layerOptions": 0,
    "shouldTrim": false
  },
  "frame": {
    "_class": "rect",
    "constrainProportions": false,
    "height": 12,
    "width": 12,
    "x": 1137,
    "y": 24
  },
  "hasClickThrough": false,
  "isFlippedHorizontal": false,
  "isFlippedVertical": false,
  "isLocked": false,
  "isVisible": false,
  "layerListExpandedType": 0,
  "layers": [
    {
      "class": "shapeGroup",
      "id": "30056E43-0D25-4942-A7CD-225DA7F19582"
    },
    {
      "class": "shapeGroup",
      "id": "B43FAD24-9ACF-4C7F-939F-2AF66F4A293E"
    }
  ],
  "name": "Close",
  "nameIsFixed": true,
  "resizingConstraint": 12,
  "resizingType": 0,
  "rotation": 0,
  "shouldBreakMaskChain": false,
  "style": {
    "_class": "style",
    "endDecorationType": 0,
    "miterLimit": 10,
    "startDecorationType": 0
  }
}