{
  "_class": "shapeGroup",
  "clippingMaskMode": 0,
  "do_objectID": "DFE88E95-1C89-4616-8D7C-AD534BAA06BB",
  "exportOptions": {
    "_class": "exportOptions",
    "exportFormats": [
    ],
    "includedLayerIds": [
    ],
    "layerOptions": 0,
    "shouldTrim": false
  },
  "frame": {
    "_class": "rect",
    "constrainProportions": false,
    "height": 229,
    "width": 316,
    "x": 0,
    "y": 0
  },
  "hasClickThrough": false,
  "hasClippingMask": false,
  "isFlippedHorizontal": false,
  "isFlippedVertical": false,
  "isLocked": false,
  "isVisible": true,
  "layerListExpandedType": 0,
  "layers": [
    {
      "class": "rectangle",
      "id": "D683A737-ECED-442F-92D7-DA5D95AC106F"
    }
  ],
  "name": "Palette / Fill / Mine Shaft",
  "nameIsFixed": true,
  "resizingConstraint": 63,
  "resizingType": 0,
  "rotation": 0,
  "shouldBreakMaskChain": false,
  "style": {
    "_class": "style",
    "endDecorationType": 0,
    "fills": [
      {
        "_class": "fill",
        "color": {
          "_class": "color",
          "alpha": 1,
          "blue": 0.2117647058823529,
          "green": 0.2117647058823529,
          "red": 0.2117647058823529
        },
        "fillType": 0,
        "isEnabled": true,
        "noiseIndex": 0,
        "noiseIntensity": 0,
        "patternFillType": 1,
        "patternTileScale": 1
      }
    ],
    "miterLimit": 10,
    "sharedObjectID": "466E5561-ABD1-44BE-9E27-F091405FC8B7",
    "startDecorationType": 0
  },
  "windingRule": 1
}