{
  "_class": "group",
  "do_objectID": "B2332693-5C3C-4A18-BA98-472776FF4A38",
  "exportOptions": {
    "_class": "exportOptions",
    "exportFormats": [
    ],
    "includedLayerIds": [
    ],
    "layerOptions": 0,
    "shouldTrim": false
  },
  "frame": {
    "_class": "rect",
    "constrainProportions": false,
    "height": 97,
    "width": 219,
    "x": 0,
    "y": 146
  },
  "hasClickThrough": false,
  "isFlippedHorizontal": false,
  "isFlippedVertical": false,
  "isLocked": false,
  "isVisible": true,
  "layerListExpandedType": 0,
  "layers": [
    {
      "class": "shapeGroup",
      "id": "E53BB519-A2AB-47BD-B271-112B19B664E4"
    },
    {
      "class": "text",
      "id": "C384CAC9-D9C4-4784-852D-6195BFD7C665"
    }
  ],
  "name": "Block Body",
  "nameIsFixed": false,
  "resizingConstraint": 63,
  "resizingType": 0,
  "rotation": 0,
  "shouldBreakMaskChain": false,
  "style": {
    "_class": "style",
    "endDecorationType": 0,
    "miterLimit": 10,
    "startDecorationType": 0
  }
}