{
  "_class": "shapePath",
  "booleanOperation": 0,
  "do_objectID": "59F70554-FB52-4B8E-AEC1-73CA80E1AC85",
  "edited": true,
  "exportOptions": {
    "_class": "exportOptions",
    "do_objectID": "D835F329-E059-4408-B5F3-750A894F91CD",
    "exportFormats": [
    ],
    "includedLayerIds": [
    ],
    "layerOptions": 0,
    "shouldTrim": false
  },
  "frame": {
    "_class": "rect",
    "constrainProportions": false,
    "do_objectID": "CFC69407-329E-4381-BA07-CAC8B20C5041",
    "height": 21.30118670129171,
    "width": 12.28222420958492,
    "x": 15.37540112578247,
    "y": 0
  },
  "isClosed": false,
  "isFlippedHorizontal": false,
  "isFlippedVertical": false,
  "isLocked": false,
  "isVisible": true,
  "layerListExpandedType": 0,
  "name": "Fill 10",
  "nameIsFixed": false,
  "pointRadiusBehaviour": 0,
  "points": [
    {
      "_class": "curvePoint",
      "cornerRadius": 0,
      "curveFrom": "{0, 0.70379005137304262}",
      "curveMode": 4,
      "curveTo": "{0, 0.49998968412799938}",
      "hasCurveFrom": true,
      "hasCurveTo": false,
      "point": "{0, 0.49998968412799938}"
    },
    {
      "_class": "curvePoint",
      "cornerRadius": 0,
      "curveFrom": "{0.80388978930307942, 0.88491613196063468}",
      "curveMode": 4,
      "curveTo": "{0.19611021069692053, 0.88491613196063468}",
      "hasCurveFrom": true,
      "hasCurveTo": true,
      "point": "{0.5, 1}"
    },
    {
      "_class": "curvePoint",
      "cornerRadius": 0,
      "curveFrom": "{1, 0.29616868513895489}",
      "curveMode": 2,
      "curveTo": "{1, 0.70381068311704387}",
      "hasCurveFrom": true,
      "hasCurveTo": true,
      "point": "{1, 0.49998968412799938}"
    },
    {
      "_class": "curvePoint",
      "cornerRadius": 0,
      "curveFrom": "{0.19611021069692053, 0.11508386803936542}",
      "curveMode": 4,
      "curveTo": "{0.80388978930307942, 0.11506323629536401}",
      "hasCurveFrom": true,
      "hasCurveTo": true,
      "point": "{0.5, 0}"
    },
    {
      "_class": "curvePoint",
      "cornerRadius": 0,
      "curveFrom": "{0, 0.49998968412799938}",
      "curveMode": 4,
      "curveTo": "{0, 0.29616868513895489}",
      "hasCurveFrom": false,
      "hasCurveTo": true,
      "point": "{0, 0.49998968412799938}"
    }
  ],
  "resizingConstraint": 63,
  "resizingType": 0,
  "rotation": 0,
  "shouldBreakMaskChain": false
}