{
  "_class": "sharedStyle",
  "do_objectID": "5F015CA4-F089-4713-81D4-712C4B573304",
  "name": "Palette / Fill / Coral Red",
  "value": {
    "_class": "style",
    "endDecorationType": 0,
    "fills": [
      {
        "_class": "fill",
        "color": {
          "_class": "color",
          "alpha": 1,
          "blue": 0.2509803921568627,
          "green": 0,
          "red": 1
        },
        "fillType": 0,
        "isEnabled": true,
        "noiseIndex": 0,
        "noiseIntensity": 0,
        "patternFillType": 1,
        "patternTileScale": 1
      }
    ],
    "miterLimit": 10,
    "sharedObjectID": "5F015CA4-F089-4713-81D4-712C4B573304",
    "startDecorationType": 0
  }
}