{
  "_class": "shapePath",
  "booleanOperation": 0,
  "do_objectID": "B01D4ADA-B944-49C0-97A9-8CF3EE17D5C6",
  "edited": true,
  "exportOptions": {
    "_class": "exportOptions",
    "exportFormats": [
    ],
    "includedLayerIds": [
    ],
    "layerOptions": 0,
    "shouldTrim": false
  },
  "frame": {
    "_class": "rect",
    "constrainProportions": false,
    "height": 6.134000000000002,
    "width": 1.334000000000001,
    "x": 10.53100000000268,
    "y": 10.40200000000004
  },
  "isFlippedHorizontal": false,
  "isFlippedVertical": false,
  "isLocked": false,
  "isVisible": true,
  "layerListExpandedType": 0,
  "name": "Shape",
  "nameIsFixed": false,
  "path": {
    "_class": "path",
    "isClosed": true,
    "pointRadiusBehaviour": 1,
    "points": [
      {
        "_class": "curvePoint",
        "cornerRadius": 0,
        "curveFrom": "{0.20164917541229374, 1}",
        "curveMode": 4,
        "curveTo": "{0.49999999999999933, 1}",
        "hasCurveFrom": true,
        "hasCurveTo": false,
        "point": "{0.49999999999999933, 1}"
      },
      {
        "_class": "curvePoint",
        "cornerRadius": 0,
        "curveFrom": "{0, 0.89126181936745985}",
        "curveMode": 4,
        "curveTo": "{0, 0.95614607107923077}",
        "hasCurveFrom": false,
        "hasCurveTo": true,
        "point": "{0, 0.89126181936745985}"
      },
      {
        "_class": "curvePoint",
        "cornerRadius": 0,
        "curveFrom": "{0, 0.043853928920769489}",
        "curveMode": 4,
        "curveTo": "{0, 0.10873818063253987}",
        "hasCurveFrom": true,
        "hasCurveTo": false,
        "point": "{0, 0.10873818063253987}"
      },
      {
        "_class": "curvePoint",
        "cornerRadius": 0,
        "curveFrom": "{0.7983508245877049, 0}",
        "curveMode": 2,
        "curveTo": "{0.20164917541229374, 0}",
        "hasCurveFrom": true,
        "hasCurveTo": true,
        "point": "{0.49999999999999933, 0}"
      },
      {
        "_class": "curvePoint",
        "cornerRadius": 0,
        "curveFrom": "{1, 0.10873818063253987}",
        "curveMode": 4,
        "curveTo": "{1, 0.043853928920769489}",
        "hasCurveFrom": false,
        "hasCurveTo": true,
        "point": "{1, 0.10873818063253987}"
      },
      {
        "_class": "curvePoint",
        "cornerRadius": 0,
        "curveFrom": "{1, 0.95614607107923022}",
        "curveMode": 4,
        "curveTo": "{1, 0.89126181936745985}",
        "hasCurveFrom": true,
        "hasCurveTo": false,
        "point": "{1, 0.89126181936745985}"
      },
      {
        "_class": "curvePoint",
        "cornerRadius": 0,
        "curveFrom": "{0.50000000000000067, 1}",
        "curveMode": 4,
        "curveTo": "{0.80284857571214285, 1}",
        "hasCurveFrom": false,
        "hasCurveTo": true,
        "point": "{0.50000000000000067, 1}"
      }
    ]
  },
  "resizingConstraint": 63,
  "resizingType": 0,
  "rotation": 0,
  "shouldBreakMaskChain": false
}