{
  "_class": "shapeGroup",
  "clippingMaskMode": 0,
  "do_objectID": "6977CF61-B5C4-4E5B-9310-C01127E26C4C",
  "exportOptions": {
    "_class": "exportOptions",
    "do_objectID": "E71AA75A-4790-44FD-BA39-ACAE4B1B66DD",
    "exportFormats": [
    ],
    "includedLayerIds": [
    ],
    "layerOptions": 0,
    "shouldTrim": false
  },
  "frame": {
    "_class": "rect",
    "constrainProportions": false,
    "do_objectID": "279C8D0D-D8DD-4580-9794-EE4CE5B7A876",
    "height": 229,
    "width": 316,
    "x": 0,
    "y": 0
  },
  "hasClickThrough": false,
  "hasClippingMask": false,
  "isFlippedHorizontal": false,
  "isFlippedVertical": false,
  "isLocked": false,
  "isVisible": true,
  "layerListExpandedType": 1,
  "layers": [
    {
      "class": "rectangle",
      "id": "973AA3E4-1EB8-4898-A29F-446992F67FF1"
    }
  ],
  "name": "Palette / Fill / White",
  "nameIsFixed": true,
  "resizingConstraint": 18,
  "resizingType": 0,
  "rotation": 0,
  "shouldBreakMaskChain": false,
  "style": {
    "_class": "style",
    "do_objectID": "ED96B2B0-214E-4B3F-81BC-E0927D0E3CCA",
    "endDecorationType": 0,
    "fills": [
      {
        "_class": "fill",
        "color": {
          "_class": "color",
          "alpha": 1,
          "blue": 0.01568627450980383,
          "green": 0.1843137254901961,
          "red": 0.6901960784313725
        },
        "fillType": 0,
        "isEnabled": true,
        "noiseIndex": 0,
        "noiseIntensity": 0,
        "patternFillType": 1,
        "patternTileScale": 1
      }
    ],
    "miterLimit": 10,
    "sharedObjectID": "CBFBE005-CE4F-4109-9069-79002C7790F6",
    "startDecorationType": 0
  },
  "windingRule": 1
}